jsignature/__init__.py
jsignature/fields.py
jsignature/forms.py
jsignature/locale/es/LC_MESSAGES/django.mo
jsignature/locale/es/LC_MESSAGES/django.po
jsignature/locale/fr/LC_MESSAGES/django.mo
jsignature/locale/fr/LC_MESSAGES/django.po
jsignature/mixins.py
jsignature/models.py
jsignature/settings.py
jsignature/static/js/django_jsignature.js
jsignature/static/js/jSignature.min.js
jsignature/templates/jsignature/widget.html
jsignature/tests/__init__.py
jsignature/tests/fields.py
jsignature/tests/forms.py
jsignature/tests/mixins.py
jsignature/tests/models.py
jsignature/tests/utils.py
jsignature/tests/widgets.py
jsignature/utils.py
jsignature/widgets.py
django_jsignature3-0.9.0.dist-info/LICENSE
django_jsignature3-0.9.0.dist-info/WHEEL
django_jsignature3-0.9.0.dist-info/METADATA
django_jsignature3-0.9.0.dist-info/RECORD
