Metadata-Version: 2.1
Name: django-jsignature3
Version: 0.9.0
Summary: Provides a simple way to handle jSignature jQuery plugin through a django form.
Home-page: https://gitlab.com/adremides/django_jsignature3/
License: LGPL-3.0+
Author: Florent Lebreton
Author-email: lebreton.florent@wanadoo.fr
Maintainer: Adremides
Maintainer-email: adremides@gmail.com
Requires-Python: >3.6
Classifier: License :: OSI Approved :: GNU Lesser General Public License v3 or later (LGPLv3+)
Classifier: Programming Language :: Python :: 3
Classifier: Programming Language :: Python :: 3.7
Classifier: Programming Language :: Python :: 3.8
Requires-Dist: django (>3.0.1)
Requires-Dist: pillow (>5.0.0)
Requires-Dist: pyquery (>1.0)
Project-URL: Repository, https://gitlab.com/adremides/django_jsignature3/
